autodiff_for_life/__init__.py
autodiff_for_life/forward_mode.py
autodiff_for_life-0.0.1.dist-info/LICENSE
autodiff_for_life-0.0.1.dist-info/METADATA
autodiff_for_life-0.0.1.dist-info/WHEEL
autodiff_for_life-0.0.1.dist-info/top_level.txt
autodiff_for_life-0.0.1.dist-info/RECORD
