Metadata-Version: 2.1
Name: autodiff-for-life
Version: 0.0.1
Summary: Auto differentiation forward mode
Home-page: UNKNOWN
Author: Lovelace Lovers (Alfred Wahlforss, Erin Tomlinson, Tyler Barnett, Xinyi Li)
Author-email: alfred@wahlforss.com
License: UNKNOWN
Keywords: python,autodiff,forward mode,automatic differentiation
Platform: UNKNOWN
Classifier: Development Status :: 1 - Planning
Classifier: Intended Audience :: Developers
Classifier: Programming Language :: Python :: 3
Classifier: Operating System :: Unix
Classifier: Operating System :: MacOS :: MacOS X
Classifier: Operating System :: Microsoft :: Windows
License-File: LICENSE
Requires-Dist: numpy
